{
  "meta": {
    "updated": "2026-05-18T11:09:26.584716Z",
    "updated_it": "18/05/2026 11:09",
    "source": "Yahoo Finance"
  },
  "data": {
    "SP500": {
      "ticker": "^GSPC",
      "n": "S&P 500",
      "ok": true,
      "price": 7408.5,
      "chg_week": 0.13,
      "ts": "2026-05-18T11:09:24.199216Z"
    },
    "STOXX": {
      "ticker": "^STOXX50E",
      "n": "Euro Stoxx 50",
      "ok": true,
      "price": 5795.46,
      "chg_week": -1.96,
      "ts": "2026-05-18T11:09:24.517727Z"
    },
    "FTSEMIB": {
      "ticker": "FTSEMIB.MI",
      "n": "FTSE MIB",
      "ok": true,
      "price": 48211.2695,
      "chg_week": -2.93,
      "ts": "2026-05-18T11:09:24.800642Z"
    },
    "DAX": {
      "ticker": "^GDAXI",
      "n": "DAX",
      "ok": true,
      "price": 23995.3809,
      "chg_week": -1.46,
      "ts": "2026-05-18T11:09:25.059307Z"
    },
    "VIX": {
      "ticker": "^VIX",
      "n": "VIX",
      "ok": true,
      "price": 19.09,
      "chg_week": 3.86,
      "ts": "2026-05-18T11:09:25.401434Z"
    },
    "US10Y": {
      "ticker": "^TNX",
      "n": "US 10Y Yield",
      "ok": true,
      "price": 4.595,
      "chg_week": 5.29,
      "ts": "2026-05-18T11:09:25.592999Z"
    },
    "EURUSD": {
      "ticker": "EURUSD=X",
      "n": "EUR/USD",
      "ok": true,
      "price": 1.1635,
      "chg_week": -1.14,
      "ts": "2026-05-18T11:09:25.832493Z"
    },
    "GOLD": {
      "ticker": "GC=F",
      "n": "Gold",
      "ok": true,
      "price": 4543.5,
      "chg_week": -3.71,
      "ts": "2026-05-18T11:09:26.085101Z"
    },
    "CRUDE": {
      "ticker": "CL=F",
      "n": "WTI Crude",
      "ok": true,
      "price": 102.42,
      "chg_week": 4.44,
      "ts": "2026-05-18T11:09:26.339963Z"
    },
    "BITCOIN": {
      "ticker": "BTC-EUR",
      "n": "Bitcoin EUR",
      "ok": true,
      "price": 65960.3984,
      "chg_week": -2.52,
      "ts": "2026-05-18T11:09:26.584633Z"
    }
  }
}